prime_tunnel/__init__.py
prime_tunnel/binary.py
prime_tunnel/exceptions.py
prime_tunnel/models.py
prime_tunnel/py.typed
prime_tunnel/tunnel.py
prime_tunnel/core/__init__.py
prime_tunnel/core/client.py
prime_tunnel/core/config.py
prime_tunnel-0.1.0.dist-info/METADATA
prime_tunnel-0.1.0.dist-info/WHEEL
prime_tunnel-0.1.0.dist-info/licenses/LICENSE
prime_tunnel-0.1.0.dist-info/RECORD
