Metadata-Version: 2.4
Name: prime-tunnel
Version: 0.1.0
Summary: Prime Intellect Tunnel SDK - Expose local services via secure tunnels
Project-URL: Homepage, https://github.com/PrimeIntellect-ai/prime-cli
Project-URL: Documentation, https://github.com/PrimeIntellect-ai/prime-cli/tree/main/packages/prime-tunnel
Project-URL: Repository, https://github.com/PrimeIntellect-ai/prime-cli.git
Author-email: Prime Intellect <contact@primeintellect.ai>
License: MIT
License-File: LICENSE
Keywords: frp,networking,reverse-proxy,sdk,tunnel
Classifier: Development Status :: 4 - Beta
Classifier: Intended Audience :: Developers
Classifier: License :: OSI Approved :: MIT License
Classifier: Operating System :: OS Independent
Classifier: Programming Language :: Python :: 3
Classifier: Programming Language :: Python :: 3.10
Classifier: Programming Language :: Python :: 3.11
Classifier: Programming Language :: Python :: 3.12
Classifier: Topic :: Software Development :: Libraries :: Python Modules
Requires-Python: >=3.10
Requires-Dist: httpx>=0.25.0
Requires-Dist: pydantic>=2.0.0
Requires-Dist: tenacity>=8.0.0
Provides-Extra: dev
Requires-Dist: pytest-asyncio>=0.23.0; extra == 'dev'
Requires-Dist: pytest-xdist>=3.0.0; extra == 'dev'
Requires-Dist: pytest>=7.0.0; extra == 'dev'
Requires-Dist: ruff>=0.13.1; extra == 'dev'
